{
  "$schema": "https://github.com/longbridge/gpui-component/raw/refs/heads/main/.theme-schema.json",
  "name": "Solarized Light",
  "author": "Ethan Schoonover",
  "url": "https://ethanschoonover.com/solarized",
  "themes": [
    {
      "name": "Solarized Light",
      "mode": "light",
      "colors": {
        "accent.background": "#eee8d5",
        "accent.foreground": "#657b83",
        "background": "#fdf6e3",
        "border": "#e8dfc8",
        "caret": "#657b83",
        "danger.background": "#dc322f",
        "danger.foreground": "#fdf6e3",
        "drag_border": "#268bd2",
        "drop_target.background": "#268bd219",
        "foreground": "#657b83",
        "info.background": "#2aa198",
        "info.foreground": "#fdf6e3",
        "input.border": "#e8dfc8",
        "link.foreground": "#268bd2",
        "link.active.foreground": "#2aa198",
        "link.hover.foreground": "#6c71c4",
        "list.background": "#fdf6e3",
        "list.active.background": "#eee8d533",
        "list.active.border": "#268bd2",
        "list.even.background": "#fdf6e366",
        "list.head.background": "#eee8d5",
        "list.hover.background": "#eee8d5",
        "muted.background": "#eee8d5",
        "muted.foreground": "#93a1a1",
        "popover.background": "#fdf6e3",
        "popover.foreground": "#657b83",
        "primary.background": "#268bd2",
        "primary.active.background": "#2196be",
        "primary.foreground": "#fdf6e3",
        "primary.hover.background": "#3094d4",
        "progress_bar.background": "#268bd2",
        "ring": "#268bd2",
        "scrollbar.background": "#fdf6e300",
        "scrollbar.thumb.background": "#93a1a1e6",
        "scrollbar.thumb.hover.background": "#93a1a1",
        "secondary.background": "#eee8d5",
        "secondary.active.background": "#d8d1be",
        "secondary.foreground": "#657b83",
        "secondary.hover.background": "#e2dccc",
        "selection.background": "#a8d4f5",
        "sidebar.background": "#eee8d5",
        "sidebar.accent.background": "#d8d1be",
        "sidebar.accent.foreground": "#586e75",
        "sidebar.border": "#d8d1be",
        "sidebar.foreground": "#586e75",
        "sidebar.primary.background": "#268bd2",
        "sidebar.primary.foreground": "#fdf6e3",
        "skeleton.background": "#eee8d5",
        "slider.bar.background": "#268bd2",
        "slider.thumb.background": "#fdf6e3",
        "success.background": "#859900",
        "success.foreground": "#fdf6e3",
        "switch.background": "#c8c0ae",
        "tab.background": "#00000000",
        "tab.active.background": "#fdf6e3",
        "tab.active.foreground": "#657b83",
        "tab_bar.background": "#eee8d5",
        "tab_bar.segmented.background": "#eee8d5",
        "tab.foreground": "#93a1a1",
        "table.background": "#fdf6e3",
        "table.head.foreground": "#93a1a1",
        "table.row.border": "#e8dfc8b3",
        "tiles.background": "#eee8d5",
        "title_bar.background": "#eee8d5",
        "title_bar.border": "#d8d1be",
        "status_bar.background": "#eee8d5",
        "status_bar.border": "#d8d1be",
        "warning.background": "#b58900",
        "warning.foreground": "#fdf6e3",
        "overlay": "#0000000d",
        "window.border": "#e8dfc8",
        "base.red": "#dc322f",
        "base.red.light": "#e34c49",
        "base.green": "#859900",
        "base.green.light": "#98aa00",
        "base.blue": "#268bd2",
        "base.blue.light": "#4099d6",
        "base.yellow": "#b58900",
        "base.yellow.light": "#c89a00",
        "base.magenta": "#d33682",
        "base.magenta.light": "#d9508e",
        "base.cyan": "#2aa198",
        "base.cyan.light": "#37b3aa"
      },
      "highlight": {
        "editor.foreground": "#657b83",
        "editor.background": "#fdf6e3",
        "editor.active_line.background": "#eee8d5",
        "editor.line_number": "#93a1a1",
        "editor.active_line_number": "#657b83",
        "editor.invisible": "#93a1a166",
        "conflict": "#dc322f",
        "created": "#859900",
        "hidden": "#93a1a1",
        "hint": "#6c71c4",
        "modified": "#b58900",
        "predictive": "#93a1a1",
        "warning": "#b58900",
        "syntax": {
          "attribute": { "color": "#859900" },
          "boolean": { "color": "#cb4b16" },
          "comment": { "color": "#93a1a1", "font_style": "italic" },
          "comment.doc": { "color": "#93a1a1", "font_style": "italic" },
          "constant": { "color": "#cb4b16" },
          "constructor": { "color": "#268bd2" },
          "embedded": { "color": "#657b83" },
          "emphasis": { "font_style": "italic" },
          "emphasis.strong": { "font_weight": 700 },
          "function": { "color": "#268bd2" },
          "keyword": { "color": "#859900" },
          "link_text": { "color": "#268bd2", "font_style": "normal" },
          "link_uri": { "color": "#93a1a1", "font_style": "italic" },
          "number": { "color": "#2aa198" },
          "string": { "color": "#2aa198" },
          "string.escape": { "color": "#dc322f" },
          "string.regex": { "color": "#2aa198" },
          "string.special": { "color": "#d33682" },
          "string.special.symbol": { "color": "#d33682" },
          "tag": { "color": "#859900" },
          "text.literal": { "color": "#2aa198" },
          "text.code.span": { "color": "#2aa198" },
          "title": { "color": "#268bd2", "font_weight": 600 },
          "type": { "color": "#b58900" },
          "property": { "color": "#657b83" },
          "variable": { "color": "#657b83" },
          "variable.special": { "color": "#dc322f" }
        }
      }
    }
  ]
}
